LICENSE
README.md
setup.py
django_pydantic_models/__init__.py
django_pydantic_models/core.py
django_pydantic_models.egg-info/PKG-INFO
django_pydantic_models.egg-info/SOURCES.txt
django_pydantic_models.egg-info/dependency_links.txt
django_pydantic_models.egg-info/requires.txt
django_pydantic_models.egg-info/top_level.txt
tests/test_all.py