Metadata-Version: 2.1
Name: django-pydantic-models
Version: 0.0.2
Summary: A lightweight utility that converts Django models into fully-typed Pydantic models.
Home-page: https://github.com/Simatwa/django-pydantic-models
Author: Smartwa
Author-email: simatwacaleb@proton.me
Maintainer: Smartwa
License: MIT
Project-URL: Bug Report, https://github.com/Simatwa/django-pydantic-models/issues/new
Project-URL: Homepage, https://github.com/Simatwa/django-pydantic-models
Project-URL: Source Code, https://github.com/Simatwa/django-pydantic-models
Project-URL: Issue Tracker, https://github.com/Simatwa/django-pydantic-models/issues
Project-URL: Download, https://github.com/Simatwa/django-pydantic-models/releases
Project-URL: Documentation, https://github.com/Simatwa/django-pydantic-models/blob/main/docs
Keywords: django,pydantic
Classifier: License :: OSI Approved :: MIT License
Classifier: Intended Audience :: Developers
Classifier: Programming Language :: Python
Classifier: Topic :: Software Development :: Libraries :: Python Modules
Classifier: Programming Language :: Python :: 3 :: Only
Classifier: Programming Language :: Python :: 3.10
Classifier: Programming Language :: Python :: 3.11
Classifier: Programming Language :: Python :: 3.12
Classifier: Programming Language :: Python :: 3.13
Requires-Python: >=3.10
License-File: LICENSE
Requires-Dist: pydantic
Requires-Dist: django
